{ "rennes2express":{
    "emission":"Rennes 2 Express",
    "edition": "2023",
    "saison": "19",
    "dates":"Du 13 au 16 novembre 2023",
    "epreuves": [
        {
            "epreuve_id": "Ep1",
            "ville": "Avignon",
            "vainqueur": "E2",
            "date": "13/11/2023 11:30",
            "type_epreuve": "quizz"
        },
        {
            "epreuve_id": "Ep2",
            "ville": "Macon",
            "vainqueur": "E4",
            "date": "14/11/2023 12:30",
            "type_epreuve": "logique"
        },
        {
            "epreuve_id": "Ep3",
            "ville": "Auxerre",
            "vainqueur": "E7",
            "date": "15/11/2023 13:00",
            "type_epreuve": "sport"
        },
        {
            "epreuve_id": "Ep4",
            "ville": "Le Mans",
            "vainqueur": "E8",
            "date": "16/11/2023 12:30",
            "type_epreuve": "adresse"
        }
    ],
    "equipes": [
        {
            "equipe_id": "E1",
            "nom": "Xavier et Céline",
            "couleur": "red"
        },
        {
            "equipe_id": "E2",
            "nom": "Inès et Anaïs",
            "couleur": "blue"
        },
        {
            "equipe_id": "E3",
            "nom": "Lucas et Nicolas",
            "couleur": "green"
        },
        {
            "equipe_id": "E4",
            "nom": "Christophe et Claire",
            "couleur": "yellow"
        },
        {
            "equipe_id": "E5",
            "nom": "Julie et Denis",
            "couleur": "pink"
        },
        {
            "equipe_id": "E6",
            "nom": "Christina et Didier",
            "couleur": "purple"
        },
        {
            "equipe_id": "E7",
            "nom": "Pierre et Jean-Pierre",
            "couleur": "orange"
        },
        {
            "equipe_id": "E8",
            "nom": "Caroline et Sabrina",
            "couleur": "brown"
        }
    ],
    "etapes": [
        {
            "code_etape": "Etape 1",
            "heure_depart": "13/11/2023 08:00",
            "lieu_depart": "Marseille",
            "borne_depart": "B01",
            "lieu_arrivee": "Avignon",
            "borne_arrivee": "B02"
        },
        {
            "code_etape": "Etape 2",
            "heure_depart": "13/11/2023 14:00",
            "lieu_depart": "Avignon",
            "borne_depart": "B03",
            "lieu_arrivee": "Lyon",
            "borne_arrivee": "B04"
        },
        {
            "code_etape": "Etape 3",
            "heure_depart": "14/11/2023 08:00",
            "lieu_depart": "Lyon",
            "borne_depart": "B05",
            "lieu_arrivee": "Macon",
            "borne_arrivee": "B06"
        },
        {
            "code_etape": "Etape 4",
            "heure_depart": "14/11/2023 14:00",
            "lieu_depart": "Macon",
            "borne_depart": "B07",
            "lieu_arrivee": "Dijon",
            "borne_arrivee": "B08"
        },
        {
            "code_etape": "Etape 5",
            "heure_depart": "15/11/2023 10:00",
            "lieu_depart": "Dijon",
            "borne_depart": "B09",
            "lieu_arrivee": "Auxerre",
            "borne_arrivee": "B10"
        },
        {
            "code_etape": "Etape 6",
            "heure_depart": "15/11/2023 15:00",
            "lieu_depart": "Auxerre",
            "borne_depart": "B11",
            "lieu_arrivee": "Paris",
            "borne_arrivee": "B12"
        },
        {
            "code_etape": "Etape 7",
            "heure_depart": "16/11/2023 09:00",
            "lieu_depart": "Paris",
            "borne_depart": "B13",
            "lieu_arrivee": "Le Mans",
            "borne_arrivee": "B14"
        },
        {
            "code_etape": "Etape 8",
            "heure_depart": "16/11/2023 15:00",
            "lieu_depart": "Le Mans",
            "borne_depart": "B15",
            "lieu_arrivee": "Rennes",
            "borne_arrivee": "B16"
        }
    ]
}
}